wtf_tinymce/__init__.py
wtf_tinymce/_version.py
wtf_tinymce/forms/__init__.py
wtf_tinymce/forms/fields.py
wtf_tinymce/forms/widgets.py
wtf_tinymce/static/vendor/tinymce/LICENSE.TXT
wtf_tinymce/static/vendor/tinymce/changelog.txt
wtf_tinymce/static/vendor/tinymce/js/tinymce/jquery.tinymce.min.js
wtf_tinymce/static/vendor/tinymce/js/tinymce/license.txt
wtf_tinymce/static/vendor/tinymce/js/tinymce/tinymce.min.js
wtf_tinymce/static/vendor/tinymce/js/tinymce/langs/readme.md
wtf_tinymce/static/vendor/tinymce/js/tinymce/plugins/advlist/plugin.min.js
wtf_tinymce/static/vendor/tinymce/js/tinymce/plugins/anchor/plugin.min.js
wtf_tinymce/static/vendor/tinymce/js/tinymce/plugins/autolink/plugin.min.js
wtf_tinymce/static/vendor/tinymce/js/tinymce/plugins/autoresize/plugin.min.js
wtf_tinymce/static/vendor/tinymce/js/tinymce/plugins/autosave/plugin.min.js
wtf_tinymce/static/vendor/tinymce/js/tinymce/plugins/bbcode/plugin.min.js
wtf_tinymce/static/vendor/tinymce/js/tinymce/plugins/charmap/plugin.min.js
wtf_tinymce/static/vendor/tinymce/js/tinymce/plugins/code/plugin.min.js
wtf_tinymce/static/vendor/tinymce/js/tinymce/plugins/codesample/plugin.min.js
wtf_tinymce/static/vendor/tinymce/js/tinymce/plugins/codesample/css/prism.css
wtf_tinymce/static/vendor/tinymce/js/tinymce/plugins/colorpicker/plugin.min.js
wtf_tinymce/static/vendor/tinymce/js/tinymce/plugins/contextmenu/plugin.min.js
wtf_tinymce/static/vendor/tinymce/js/tinymce/plugins/directionality/plugin.min.js
wtf_tinymce/static/vendor/tinymce/js/tinymce/plugins/emoticons/plugin.min.js
wtf_tinymce/static/vendor/tinymce/js/tinymce/plugins/emoticons/img/smiley-cool.gif
wtf_tinymce/static/vendor/tinymce/js/tinymce/plugins/emoticons/img/smiley-cry.gif
wtf_tinymce/static/vendor/tinymce/js/tinymce/plugins/emoticons/img/smiley-embarassed.gif
wtf_tinymce/static/vendor/tinymce/js/tinymce/plugins/emoticons/img/smiley-foot-in-mouth.gif
wtf_tinymce/static/vendor/tinymce/js/tinymce/plugins/emoticons/img/smiley-frown.gif
wtf_tinymce-0.1.4.dist-info/LICENSE
wtf_tinymce-0.1.4.dist-info/METADATA
wtf_tinymce-0.1.4.dist-info/WHEEL
wtf_tinymce-0.1.4.dist-info/top_level.txt
wtf_tinymce-0.1.4.dist-info/RECORD
