Metadata-Version: 2.1
Name: wtf-tinymce
Version: 0.1.4
Summary: TinyMCE editor extension for WTForms
Home-page: https://github.com/azsoftware/wtf-tinymce
Author: Alexander Zhygailo
Author-email: alexander777vz@gmail.com
License: GNU General Public License v3 (GPLv3)
Keywords: wtf-tinymce,wtforms,tinymce,richeditor
Platform: UNKNOWN
Classifier: Programming Language :: Python
Classifier: Programming Language :: Python :: 2.7
Classifier: Programming Language :: Python :: 3.5
Classifier: License :: OSI Approved :: GNU General Public License v3 (GPLv3)
Classifier: Operating System :: OS Independent
Classifier: Intended Audience :: Developers
Classifier: Development Status :: 5 - Production/Stable
Classifier: Topic :: Software Development :: Libraries
License-File: LICENSE
Requires-Dist: bleach
Requires-Dist: WTForms (>=2.0)
Requires-Dist: Flask (>=0.10.0)
Requires-Dist: Flask-WTF
